toytools/__init__.py
toytools/cli.py
toytools/io/__init__.py
toytools/io/file.py
toytools-0.1.0.dist-info/METADATA
toytools-0.1.0.dist-info/RECORD
toytools-0.1.0.dist-info/WHEEL
toytools-0.1.0.dist-info/entry_points.txt
toytools-0.1.0.dist-info/top_level.txt
