Metadata-Version: 2.1
Name: toytools
Version: 0.1.0
Summary: toytools is a personal tool for misc things.
Home-page: https://github.com/yujiepan/toytools
Author: yujiepan
Author-email: yujiepan@sjtu.edu.cn
License: MIT license
Keywords: toytools
Platform: UNKNOWN
Classifier: Development Status :: 2 - Pre-Alpha
Classifier: Intended Audience :: Developers
Classifier: License :: OSI Approved :: MIT License
Classifier: Natural Language :: English
Classifier: Programming Language :: Python :: 3
Classifier: Programming Language :: Python :: 3.6
Classifier: Programming Language :: Python :: 3.7
Classifier: Programming Language :: Python :: 3.8
Requires-Python: >=3.6
